entropec_quantumoperator_test/__init__.py
entropec_quantumoperator_test/core.py
qumulator-0.1.0.dist-info/licenses/LICENSE
qumulator-0.1.0.dist-info/METADATA
qumulator-0.1.0.dist-info/WHEEL
qumulator-0.1.0.dist-info/top_level.txt
qumulator-0.1.0.dist-info/RECORD
